MANIFEST.in
README.md
setup.py
abiquo/__init__.py
abiquo/auth.py
abiquo/client.py
abiquo_api.egg-info/PKG-INFO
abiquo_api.egg-info/SOURCES.txt
abiquo_api.egg-info/dependency_links.txt
abiquo_api.egg-info/requires.txt
abiquo_api.egg-info/top_level.txt