Metadata-Version: 1.1
Name: abiquo-api
Version: 0.1.12
Summary: Abiquo API Python Client
Home-page: https://github.com/abiquo/api-python-client
Author: Abiquo
Author-email: developers@abiquo.com
License: Apache License 2.0
Keywords: abiquo api rest
Platform: UNKNOWN
Classifier: Development Status :: 4 - Beta
Classifier: Intended Audience :: Developers
Classifier: Intended Audience :: System Administrators
Classifier: License :: OSI Approved :: Apache Software License
Classifier: Operating System :: MacOS :: MacOS X
Classifier: Operating System :: Microsoft :: Windows
Classifier: Operating System :: POSIX
Classifier: Programming Language :: Python
Classifier: Topic :: Software Development :: Libraries :: Python Modules
Classifier: Topic :: Utilities
